dash_react_resizeable/DashReactResizeable.py
dash_react_resizeable/__init__.py
dash_react_resizeable/_imports_.py
dash_react_resizeable/dash_react_resizeable.dev.js
dash_react_resizeable/dash_react_resizeable.min.js
dash_react_resizeable/metadata.json
dash_react_resizeable/package.json
dash_react_resizeable-0.0.1.dist-info/DESCRIPTION.rst
dash_react_resizeable-0.0.1.dist-info/METADATA
dash_react_resizeable-0.0.1.dist-info/RECORD
dash_react_resizeable-0.0.1.dist-info/WHEEL
dash_react_resizeable-0.0.1.dist-info/metadata.json
dash_react_resizeable-0.0.1.dist-info/top_level.txt
