Metadata-Version: 2.0
Name: dash-react-resizeable
Version: 0.0.1
Summary: A dash component built on the react resizeable component
Home-page: UNKNOWN
Author: Alberto Gutierrez albertogutierrez826@gmail.com
Author-email: UNKNOWN
License: MIT
Platform: UNKNOWN
